README.md
setup.py
pyem18/__init__.py
pyem18/pyem18.py
pyem18.egg-info/PKG-INFO
pyem18.egg-info/SOURCES.txt
pyem18.egg-info/dependency_links.txt
pyem18.egg-info/requires.txt
pyem18.egg-info/top_level.txt