Metadata-Version: 1.0
Name: pyem18
Version: 0.1
Summary: A Python library to read data from EM-18 RFID reader module
Home-page: http://github.com/dhavalsavalia/pyem18
Author: Dhaval Savalia
Author-email: dhaval.savalia6@gmail.com
License: MIT
Keywords: em18 rfid reader
Platform: UNKNOWN
